wage_labor_record/__init__.py
wage_labor_record/actions.py
wage_labor_record/time_tracker_tray_icon.py
wage_labor_record/time_tracker_window.py
wage_labor_record/tracking_state.py
wage_labor_record/utils.py
wage_labor_record/wlr_app.py
wage_labor_record/worked_time_store.py
wage_labor_record/history_view/__init__.py
wage_labor_record/history_view/datetime_picker.py
wage_labor_record/history_view/history_browser_window.py
wage_labor_record/history_view/selector_widget.py
wage_labor_record/history_view/summary_view.py
wage_labor_record/history_view/worked_times_list_view.py
wage_labor_record/resources/__init__.py
wage_labor_record/resources/start-tracking.svg
wage_labor_record/resources/stop-tracking-disabled.svg
wage_labor_record/resources/stop-tracking.svg
wage_labor_record-0.2.dist-info/LICENSE
wage_labor_record-0.2.dist-info/METADATA
wage_labor_record-0.2.dist-info/WHEEL
wage_labor_record-0.2.dist-info/entry_points.txt
wage_labor_record-0.2.dist-info/top_level.txt
wage_labor_record-0.2.dist-info/RECORD
