Metadata-Version: 2.1
Name: wage-labor-record
Version: 0.2
Summary: A tool to track you wage labor.
Author-email: Maximilian Ernestus <maximilian@ernestus.de>
License: GNU GENERAL PUBLIC LICENSE
Keywords: timetracking
Classifier: Development Status :: 3 - Alpha
Classifier: Environment :: X11 Applications :: GTK
Classifier: Intended Audience :: End Users/Desktop
Classifier: License :: OSI Approved :: GNU General Public License v3 (GPLv3)
Classifier: Natural Language :: English
Classifier: Operating System :: POSIX :: Linux
Classifier: Programming Language :: Python :: 3
Classifier: Topic :: Office/Business :: Financial :: Accounting
Classifier: Topic :: Utilities
Requires-Python: >=3.8
License-File: LICENSE
Requires-Dist: PyGObject
